modern/__init__.py
modern/celery.py
modern/config.py
modern/database.py
modern/flask.py
modern/observability.py
modern/redis.py
modern/storage.py
modern_flask-202207b1.dist-info/LICENSE
modern_flask-202207b1.dist-info/METADATA
modern_flask-202207b1.dist-info/WHEEL
modern_flask-202207b1.dist-info/top_level.txt
modern_flask-202207b1.dist-info/RECORD
