Metadata-Version: 2.1
Name: modern-flask
Version: 202207b1
Summary: modern flask framework
Home-page: https://gitee.com/modernapps/modern-flask
Author: guoyk93
Author-email: hi@guoyk.net
License: MIT
Platform: UNKNOWN
Classifier: Environment :: Web Environment
Classifier: Operating System :: OS Independent
Classifier: Topic :: Internet :: WWW/HTTP
Classifier: License :: OSI Approved :: MIT License
Classifier: Programming Language :: Python :: 3
Classifier: Programming Language :: Python :: 3.7
Classifier: Framework :: Flask
Requires-Dist: Flask (==2.1.3)
Requires-Dist: PyMySQL (==1.0.2)
Requires-Dist: SQLAlchemy (==1.4.39)
Requires-Dist: celery[redis] (==5.2.7)
Requires-Dist: cos-python-sdk-v5 (==1.9.20)
Requires-Dist: gunicorn (==20.1.0)
Requires-Dist: kubernetes (==22.6.0)
Requires-Dist: opentelemetry-api (==1.11.1)
Requires-Dist: opentelemetry-exporter-jaeger-thrift (==1.11.1)
Requires-Dist: opentelemetry-exporter-zipkin-json (==1.11.1)
Requires-Dist: opentelemetry-instrumentation-flask (==0.30b1)
Requires-Dist: opentelemetry-instrumentation-logging (==0.30b1)
Requires-Dist: opentelemetry-instrumentation-redis (==0.30b1)
Requires-Dist: opentelemetry-instrumentation-requests (==0.30b1)
Requires-Dist: opentelemetry-instrumentation-sqlalchemy (==0.30b1)
Requires-Dist: opentelemetry-propagator-b3 (==1.11.1)
Requires-Dist: opentelemetry-sdk (==1.11.1)
Requires-Dist: oss2 (==2.15.0)
Requires-Dist: prometheus-client (==0.14.1)
Requires-Dist: redis (==4.1.4)
Requires-Dist: requests (==2.28.1)
